{
  "info": {
    "_postman_id": "5f98e1e8-3dca-4a67-bc73-d07a86b09a28",
    "name": "Prueba técnica Supermercado",
    "schema": "https://schema.getpostman.com/json/collection/v2.1.0/collection.json",
    "_exporter_id": "42583743"
  },
  "item": [
    {
      "name": "login",
      "request": {
        "auth": {
          "type": "noauth"
        },
        "method": "POST",
        "header": [],
        "body": {
          "mode": "raw",
          "raw": "{\r\n    \"username\": \"admin\",\r\n    \"password\": \"admin\"\r\n}",
          "options": {
            "raw": {
              "language": "json"
            }
          }
        },
        "url": {
          "raw": "{{base_url}}/api/auth/login",
          "host": [
            "{{base_url}}"
          ],
          "path": [
            "api",
            "auth",
            "login"
          ]
        }
      },
      "response": []
    },
    {
      "name": "registroUsuario",
      "request": {
        "method": "POST",
        "header": [],
        "body": {
          "mode": "raw",
          "raw": "{\r\n    \"nombre\": \"John\",\r\n    \"username\": \"john123\",\r\n    \"password\": \"123\"\r\n}",
          "options": {
            "raw": {
              "language": "json"
            }
          }
        },
        "url": {
          "raw": "{{base_url}}/api/auth/registro",
          "host": [
            "{{base_url}}"
          ],
          "path": [
            "api",
            "auth",
            "registro"
          ]
        }
      },
      "response": []
    },
    {
      "name": "GET productos",
      "request": {
        "auth": {
          "type": "bearer",
          "bearer": [
            {
              "key": "token",
              "value": "",
              "type": "string"
            }
          ]
        },
        "method": "GET",
        "header": [],
        "url": {
          "raw": "{{base_url}}/api/productos",
          "host": [
            "{{base_url}}"
          ],
          "path": [
            "api",
            "productos"
          ]
        }
      },
      "response": []
    },
    {
      "name": "POST producto",
      "request": {
        "auth": {
          "type": "bearer",
          "bearer": [
            {
              "key": "token",
              "value": "",
              "type": "string"
            }
          ]
        },
        "method": "POST",
        "header": [],
        "body": {
          "mode": "raw",
          "raw": "{\r\n    \"nombre\": \"Fanta 2.5lts\",\r\n    \"precioActual\": 2600.75,\r\n    \"cantidad\": 60,\r\n    \"categoria\": \"BEBIDAS\"\r\n}",
          "options": {
            "raw": {
              "language": "json"
            }
          }
        },
        "url": {
          "raw": "{{base_url}}/api/productos",
          "host": [
            "{{base_url}}"
          ],
          "path": [
            "api",
            "productos"
          ]
        }
      },
      "response": []
    },
    {
      "name": "GET sucursales",
      "request": {
        "auth": {
          "type": "bearer",
          "bearer": [
            {
              "key": "token",
              "value": "",
              "type": "string"
            }
          ]
        },
        "method": "GET",
        "header": [],
        "url": {
          "raw": "{{base_url}}/api/sucursales",
          "host": [
            "{{base_url}}"
          ],
          "path": [
            "api",
            "sucursales"
          ]
        }
      },
      "response": []
    },
    {
      "name": "POST sucursal",
      "request": {
        "auth": {
          "type": "bearer",
          "bearer": [
            {
              "key": "token",
              "value": "",
              "type": "string"
            }
          ]
        },
        "method": "POST",
        "header": [],
        "body": {
          "mode": "raw",
          "raw": "{\r\n    \"nombre\": \"Sucursal Zanjón\",\r\n    \"direccion\": \"Robles 188\"\r\n}",
          "options": {
            "raw": {
              "language": "json"
            }
          }
        },
        "url": {
          "raw": "{{base_url}}/api/sucursales",
          "host": [
            "{{base_url}}"
          ],
          "path": [
            "api",
            "sucursales"
          ]
        }
      },
      "response": []
    },
    {
      "name": "POST venta",
      "request": {
        "auth": {
          "type": "bearer",
          "bearer": [
            {
              "key": "token",
              "value": "",
              "type": "string"
            }
          ]
        },
        "method": "POST",
        "header": [],
        "body": {
          "mode": "raw",
          "raw": "{\r\n    \"fecha\": \"2025-01-10\",\r\n    \"estado\": \"COMPLETADA\",\r\n    \"idSucursal\": 1,\r\n    \"ventaDetalleDTOList\": [\r\n        {\r\n            \"idProd\": 1,\r\n            \"precioUnitario\": 2600.75,\r\n            \"nombreProd\": \"Fanta 2.5lts\",\r\n            \"cantidadProd\": 2,\r\n            \"subtotal\": 5201.5\r\n        }\r\n    ],\r\n    \"precioTotal\": 5201.5\r\n}",
          "options": {
            "raw": {
              "language": "json"
            }
          }
        },
        "url": {
          "raw": "{{base_url}}/api/ventas",
          "host": [
            "{{base_url}}"
          ],
          "path": [
            "api",
            "ventas"
          ]
        }
      },
      "response": []
    },
    {
      "name": "GET ventas",
      "protocolProfileBehavior": {
        "disableBodyPruning": true
      },
      "request": {
        "auth": {
          "type": "bearer",
          "bearer": [
            {
              "key": "token",
              "value": "",
              "type": "string"
            }
          ]
        },
        "method": "GET",
        "header": [],
        "body": {
          "mode": "raw",
          "raw": "{\r\n    \"nombre\": \"Sucursal Zanjón\",\r\n    \"direccion\": \"Robles 188\"\r\n}"
        },
        "url": {
          "raw": "{{base_url}}/api/ventas",
          "host": [
            "{{base_url}}"
          ],
          "path": [
            "api",
            "ventas"
          ]
        }
      },
      "response": []
    },
    {
      "name": "GET producto By ID",
      "request": {
        "auth": {
          "type": "bearer",
          "bearer": [
            {
              "key": "token",
              "value": "",
              "type": "string"
            }
          ]
        },
        "method": "GET",
        "header": [],
        "url": {
          "raw": "{{base_url}}/api/productos/1",
          "host": [
            "{{base_url}}"
          ],
          "path": [
            "api",
            "productos",
            "1"
          ]
        }
      },
      "response": []
    },
    {
      "name": "GET sucursal by ID",
      "request": {
        "auth": {
          "type": "bearer",
          "bearer": [
            {
              "key": "token",
              "value": "",
              "type": "string"
            }
          ]
        },
        "method": "GET",
        "header": [],
        "url": {
          "raw": "{{base_url}}/api/sucursales/1",
          "host": [
            "{{base_url}}"
          ],
          "path": [
            "api",
            "sucursales",
            "1"
          ]
        }
      },
      "response": []
    },
    {
      "name": "GET producto mas vendido",
      "request": {
        "auth": {
          "type": "bearer",
          "bearer": [
            {
              "key": "token",
              "value": "",
              "type": "string"
            }
          ]
        },
        "method": "GET",
        "header": [],
        "url": {
          "raw": "{{base_url}}/api/ventas/producto_mas_vendido",
          "host": [
            "{{base_url}}"
          ],
          "path": [
            "api",
            "ventas",
            "producto_mas_vendido"
          ]
        }
      },
      "response": []
    },
    {
      "name": "GET carrito",
      "protocolProfileBehavior": {
        "disableBodyPruning": true
      },
      "request": {
        "auth": {
          "type": "bearer",
          "bearer": [
            {
              "key": "token",
              "value": "",
              "type": "string"
            }
          ]
        },
        "method": "GET",
        "header": [],
        "body": {
          "mode": "raw",
          "raw": ""
        },
        "url": {
          "raw": "{{base_url}}/api/carrito/mi-carrito",
          "host": [
            "{{base_url}}"
          ],
          "path": [
            "api",
            "carrito",
            "mi-carrito"
          ]
        }
      },
      "response": []
    },
    {
      "name": "Agregar Producto",
      "request": {
        "auth": {
          "type": "bearer",
          "bearer": [
            {
              "key": "token",
              "value": "",
              "type": "string"
            }
          ]
        },
        "method": "POST",
        "header": [],
        "body": {
          "mode": "raw",
          "raw": ""
        },
        "url": {
          "raw": "{{base_url}}/api/carrito/1/producto/1?cantidad=2",
          "host": [
            "{{base_url}}"
          ],
          "path": [
            "api",
            "carrito",
            "1",
            "producto",
            "1"
          ],
          "query": [
            {
              "key": "cantidad",
              "value": "2"
            }
          ]
        }
      },
      "response": []
    },
    {
      "name": "Quitar producto",
      "request": {
        "auth": {
          "type": "bearer",
          "bearer": [
            {
              "key": "token",
              "value": "",
              "type": "string"
            }
          ]
        },
        "method": "DELETE",
        "header": [],
        "body": {
          "mode": "raw",
          "raw": ""
        },
        "url": {
          "raw": "{{base_url}}/api/carrito/1/producto/1?cantidad=1",
          "host": [
            "{{base_url}}"
          ],
          "path": [
            "api",
            "carrito",
            "1",
            "producto",
            "1"
          ],
          "query": [
            {
              "key": "cantidad",
              "value": "1"
            }
          ]
        }
      },
      "response": []
    },
    {
      "name": "Finalizar compra",
      "request": {
        "auth": {
          "type": "bearer",
          "bearer": [
            {
              "key": "token",
              "value": "",
              "type": "string"
            }
          ]
        },
        "method": "POST",
        "header": [],
        "body": {
          "mode": "raw",
          "raw": ""
        },
        "url": {
          "raw": "{{base_url}}/api/carrito/1/checkout/1",
          "host": [
            "{{base_url}}"
          ],
          "path": [
            "api",
            "carrito",
            "1",
            "checkout",
            "1"
          ]
        }
      },
      "response": []
    }
  ],
  "event": [
    {
      "listen": "prerequest",
      "script": {
        "type": "text/javascript",
        "packages": {},
        "requests": {},
        "exec": [
          ""
        ]
      }
    },
    {
      "listen": "test",
      "script": {
        "type": "text/javascript",
        "packages": {},
        "requests": {},
        "exec": [
          ""
        ]
      }
    }
  ],
  "variable": [
    {
      "key": "base_url",
      "value": ""
    }
  ]
}